{
  "capabilities_cache": [],
  "component_sources": [
    {
      "id": "messaging-provider-webex",
      "version": "0.4.37",
      "world": "greentic:component/component-v0-v6-v0@0.6.1",
      "supports": [
        "messaging"
      ],
      "profiles": {
        "default": "default",
        "supported": [
          "default"
        ]
      },
      "capabilities": {
        "wasi": {
          "random": false,
          "clocks": false
        },
        "host": {
          "secrets-store": true,
          "http-client": true
        }
      },
      "wasm": "components/messaging-provider-webex/component.wasm"
    },
    {
      "id": "ai.greentic.component-provision",
      "version": "0.4.37",
      "world": "greentic:component/component@0.5.0",
      "supports": [
        "messaging"
      ],
      "profiles": {
        "default": "stateless",
        "supported": [
          "stateless"
        ]
      },
      "capabilities": {
        "host": {
          "state": {
            "delete": false,
            "read": false,
            "write": true
          },
          "telemetry": {
            "scope": "node"
          }
        },
        "wasi": {
          "clocks": false,
          "filesystem": {
            "mode": "none",
            "mounts": []
          },
          "random": false
        }
      },
      "wasm": "components/provision/provision.wasm"
    },
    {
      "id": "ai.greentic.component-qa",
      "version": "0.4.37",
      "world": "greentic:component/component@0.5.0",
      "supports": [
        "messaging"
      ],
      "profiles": {
        "default": "stateless",
        "supported": [
          "stateless"
        ]
      },
      "capabilities": {
        "host": {
          "messaging": {
            "inbound": true,
            "outbound": true
          },
          "qa": {
            "process": true
          },
          "secrets": {
            "required": []
          },
          "telemetry": {
            "scope": "node"
          }
        },
        "wasi": {
          "clocks": true,
          "filesystem": {
            "mode": "none",
            "mounts": []
          },
          "random": true
        }
      },
      "wasm": "components/qa/qa.wasm"
    }
  ],
  "components": [
    "messaging-provider-webex",
    "ai.greentic.component-provision",
    "ai.greentic.component-qa"
  ],
  "config_schema": {
    "provider_config": {
      "format": "json",
      "path": "schemas/messaging/webex/public.config.schema.json"
    }
  },
  "description": "Provider-core Webex messaging pack (messages API).",
  "extensions": {
    "greentic.ext.capabilities.v1": {
      "kind": "greentic.ext.capabilities.v1",
      "version": "0.4.37",
      "inline": {
        "schema_version": 1,
        "offers": [
          {
            "offer_id": "messaging-webex-v1",
            "cap_id": "greentic.cap.messaging.provider.v1",
            "version": "0.4.37",
            "provider": {
              "component_ref": "messaging-provider-webex",
              "op": "messaging.configure"
            },
            "priority": 100,
            "requires_setup": true,
            "setup": {
              "qa_ref": "setup.yaml"
            }
          }
        ]
      }
    },
    "greentic.messaging.validators.v1": {
      "kind": "greentic.messaging.validators.v1",
      "version": "0.4.37",
      "inline": {
        "validators": [
          {
            "component_ref": "oci://ghcr.io/greenticai/validators/messaging:0.4.19",
            "id": "greentic.validators.messaging",
            "world": "greentic:pack-validate/pack-validator@0.1.0"
          }
        ]
      }
    },
    "greentic.provider-extension.v1": {
      "kind": "greentic.provider-extension.v1",
      "version": "0.4.37",
      "inline": {
        "providers": [
          {
            "provider_type": "messaging.webex.bot",
            "capabilities": [
              "messaging"
            ],
            "ops": [
              "send",
              "reply",
              "qa-spec",
              "apply-answers",
              "i18n-keys"
            ],
            "config_schema_ref": "schemas/messaging/webex/public.config.schema.json",
            "runtime": {
              "component_ref": "messaging-provider-webex",
              "export": "schema-core-api",
              "world": "greentic:provider/schema-core@1.0.0"
            }
          }
        ]
      }
    },
    "messaging.provider_flow_hints": {
      "kind": "messaging.provider_flow_hints",
      "version": "0.4.37",
      "inline": {
        "messaging.webex.bot": {
          "default": "default",
          "diagnostics": "diagnostics",
          "remove": "remove",
          "setup_default": "setup_default",
          "update": "update",
          "verify_webhooks": "verify_webhooks"
        }
      }
    }
  },
  "flows": [
    {
      "id": "default",
      "file": "flows/default.ygtc",
      "tags": [
        "default"
      ],
      "entrypoints": [
        "default"
      ]
    },
    {
      "id": "diagnostics",
      "file": "flows/diagnostics.ygtc",
      "tags": [
        "default"
      ],
      "entrypoints": [
        "diagnostics"
      ]
    },
    {
      "id": "remove",
      "file": "flows/remove.ygtc",
      "tags": [
        "default"
      ],
      "entrypoints": [
        "remove"
      ]
    },
    {
      "id": "setup_default",
      "file": "flows/setup_default.ygtc",
      "tags": [
        "default"
      ],
      "entrypoints": [
        "setup"
      ]
    },
    {
      "id": "requirements",
      "file": "flows/requirements.ygtc",
      "tags": [
        "default"
      ],
      "entrypoints": [
        "requirements"
      ]
    },
    {
      "id": "sync_subscriptions",
      "file": "flows/sync_subscriptions.ygtc",
      "tags": [
        "default"
      ],
      "entrypoints": [
        "subscriptions"
      ]
    },
    {
      "id": "update",
      "file": "flows/update.ygtc",
      "tags": [
        "default"
      ],
      "entrypoints": [
        "update"
      ]
    },
    {
      "id": "verify_webhooks",
      "file": "flows/verify_webhooks.ygtc",
      "tags": [
        "default"
      ],
      "entrypoints": [
        "verify_webhooks"
      ]
    }
  ],
  "kind": "application",
  "messaging": {
    "adapters": [
      {
        "component": "messaging-provider-webex",
        "kind": "egress",
        "name": "messaging.webex.bot"
      }
    ]
  },
  "name": "messaging-webex",
  "publisher": "Greentic",
  "secret_requirements": [
    {
      "name": "WEBEX_BOT_TOKEN",
      "scope": "tenant",
      "description": "Webex bot access token used for Messages API calls."
    }
  ],
  "version": "0.4.37"
}
