{
  "name": "messaging-dummy",
  "version": "0.4.15",
  "description": "Deterministic provider-core messaging provider for CI and integration tests.",
  "kind": "application",
  "publisher": "Greentic",
  "config_schema": {
    "provider_config": {
      "format": "json",
      "path": "schemas/messaging/dummy/config.schema.json"
    }
  },
  "components": [
    "messaging-provider-dummy"
  ],
  "extensions": {
    "greentic.provider-extension.v1": {
      "kind": "greentic.provider-extension.v1",
      "version": "0.4.14",
      "inline": {
        "providers": [
          {
            "provider_type": "messaging.dummy",
            "capabilities": [
              "messaging"
            ],
            "ops": [
              "send"
            ],
            "config_schema_ref": "schemas/messaging/dummy/config.schema.json",
            "state_schema_ref": "",
            "runtime": {
              "component_ref": "messaging-provider-dummy",
              "export": "schema-core-api",
              "world": "greentic:provider/schema-core@1.0.0"
            },
            "docs_ref": ""
          }
        ]
      }
    },
    "messaging.provider_flow_hints": {
      "kind": "messaging.provider_flow_hints",
      "version": "0.4.14",
      "inline": {
        "messaging.dummy": {
          "diagnostics": "diagnostics",
          "setup_custom": "setup_custom",
          "setup_default": "setup_default"
        }
      }
    }
  },
  "secret_requirements": [],
  "flows": [
    {
      "id": "diagnostics",
      "file": "flows/diagnostics.ygtc",
      "tags": [
        "default"
      ],
      "entrypoints": [
        "diagnostics"
      ]
    },
    {
      "id": "requirements",
      "file": "flows/requirements.ygtc",
      "tags": [
        "default"
      ],
      "entrypoints": [
        "requirements"
      ]
    },
    {
      "id": "setup_custom",
      "file": "flows/setup_custom.ygtc",
      "tags": [
        "default"
      ],
      "entrypoints": [
        "setup"
      ]
    },
    {
      "id": "setup_default",
      "file": "flows/setup_default.ygtc",
      "tags": [
        "default"
      ],
      "entrypoints": [
        "setup"
      ]
    }
  ],
  "component_sources": [
    {
      "id": "messaging-provider-dummy",
      "version": "0.4.14",
      "world": "greentic:provider/schema-core@1.0.0",
      "supports": [
        "messaging"
      ],
      "profiles": {
        "default": "default",
        "supported": [
          "default"
        ]
      },
      "capabilities": {
        "wasi": {
          "random": false,
          "clocks": false
        },
        "host": {}
      },
      "wasm": "components/messaging-provider-dummy.wasm"
    }
  ],
  "capabilities_cache": [
    {
      "component": "ai.greentic.component-templates",
      "version": "v1",
      "path": "components/ai.greentic.component-templates-capabilities_v1.json"
    }
  ]
}
